{
  "version": "2.4.1",
  "summary": {
    "title": "Stellar Pay Digital Banking",
    "owner": "Nepo",
    "description": "Threat model for the Stellar Pay web--based digital payment platform",
    "id": 0
  },
  "detail": {
    "contributors": [],
    "diagrams": [
      {
        "id": 1,
        "title": "StellarPayAppModel",
        "diagramType": "STRIDE",
        "placeholder": "New STRIDE diagram description",
        "thumbnail": "./public/content/images/thumbnail.stride.jpg",
        "version": "2.4.1",
        "cells": [
          {
            "position": {
              "x": 72.24999999999932,
              "y": 40.00000000000357
            },
            "size": {
              "width": 850,
              "height": 130
            },
            "attrs": {
              "label": {
                "text": "External Network"
              }
            },
            "visible": true,
            "shape": "trust-boundary-box",
            "id": "c7356444-1863-4d99-a939-f86a2d39b58a",
            "zIndex": -1,
            "data": {
              "type": "tm.BoundaryBox",
              "name": "External Network",
              "description": "",
              "isTrustBoundary": true,
              "hasOpenThreats": false
            }
          },
          {
            "position": {
              "x": 339.5,
              "y": 460
            },
            "size": {
              "width": 140,
              "height": 130
            },
            "attrs": {
              "label": {
                "text": "Web Application Internal"
              }
            },
            "visible": true,
            "shape": "trust-boundary-box",
            "id": "8b0e21c7-8a88-4ae1-8100-3167bd99b9a1",
            "zIndex": -1,
            "data": {
              "type": "tm.BoundaryBox",
              "name": "Web Application Internal",
              "description": "",
              "isTrustBoundary": true,
              "hasOpenThreats": false
            }
          },
          {
            "position": {
              "x": 558,
              "y": 175
            },
            "size": {
              "width": 340,
              "height": 90
            },
            "attrs": {
              "label": {
                "text": "Web Application Internal"
              }
            },
            "visible": true,
            "shape": "trust-boundary-box",
            "id": "b9c630b2-2418-4d0b-913a-2a7c3ee06658",
            "zIndex": -1,
            "data": {
              "type": "tm.BoundaryBox",
              "name": "Web Application Internal",
              "description": "",
              "isTrustBoundary": true,
              "hasOpenThreats": false
            }
          },
          {
            "position": {
              "x": 80,
              "y": 159.99999999999994
            },
            "size": {
              "width": 140,
              "height": 110
            },
            "attrs": {
              "label": {
                "text": "Web Application Internal"
              }
            },
            "visible": true,
            "shape": "trust-boundary-box",
            "id": "889214e2-1d31-47d8-9e97-2f671e52c5b3",
            "zIndex": -1,
            "data": {
              "type": "tm.BoundaryBox",
              "name": "Web Application Internal",
              "description": "",
              "isTrustBoundary": true,
              "hasOpenThreats": false
            }
          },
          {
            "position": {
              "x": 72.24999999999932,
              "y": 400
            },
            "size": {
              "width": 950,
              "height": 60
            },
            "attrs": {
              "label": {
                "text": "Data Storage Zone"
              }
            },
            "visible": true,
            "shape": "trust-boundary-box",
            "id": "4eb3cabb-f24e-4e08-858f-cd38665ff5ba",
            "zIndex": -1,
            "data": {
              "type": "tm.BoundaryBox",
              "name": "Data Storage Zone",
              "description": "",
              "isTrustBoundary": true,
              "hasOpenThreats": false
            }
          },
          {
            "position": {
              "x": 80,
              "y": 40
            },
            "size": {
              "width": 112.5,
              "height": 60
            },
            "attrs": {
              "text": {
                "text": "User"
              },
              "body": {
                "stroke": "#333333",
                "strokeWidth": 1.5,
                "strokeDasharray": null
              }
            },
            "visible": true,
            "shape": "actor",
            "ports": {
              "groups": {
                "top": {
                  "position": "top",
                  "attrs": {
                    "circle": {
                      "r": 4,
                      "magnet": true,
                      "stroke": "#5F95FF",
                      "strokeWidth": 1,
                      "fill": "#fff",
                      "style": {
                        "visibility": "hidden"
                      }
                    }
                  }
                },
                "right": {
                  "position": "right",
                  "attrs": {
                    "circle": {
                      "r": 4,
                      "magnet": true,
                      "stroke": "#5F95FF",
                      "strokeWidth": 1,
                      "fill": "#fff",
                      "style": {
                        "visibility": "hidden"
                      }
                    }
                  }
                },
                "bottom": {
                  "position": "bottom",
                  "attrs": {
                    "circle": {
                      "r": 4,
                      "magnet": true,
                      "stroke": "#5F95FF",
                      "strokeWidth": 1,
                      "fill": "#fff",
                      "style": {
                        "visibility": "hidden"
                      }
                    }
                  }
                },
                "left": {
                  "position": "left",
                  "attrs": {
                    "circle": {
                      "r": 4,
                      "magnet": true,
                      "stroke": "#5F95FF",
                      "strokeWidth": 1,
                      "fill": "#fff",
                      "style": {
                        "visibility": "hidden"
                      }
                    }
                  }
                }
              },
              "items": [
                {
                  "group": "top",
                  "id": "153955eb-57cb-4855-8cd1-f81644e71db9"
                },
                {
                  "group": "right",
                  "id": "a05692a4-6712-4d97-9964-84bad8ed7c31"
                },
                {
                  "group": "bottom",
                  "id": "0db3e927-0339-4b5e-a037-55e00d40eda3"
                },
                {
                  "group": "left",
                  "id": "27d78f95-7623-4018-ad09-dd3669f7077b"
                }
              ]
            },
            "id": "8ddb3e65-40db-43a5-ae79-f6d4bd2789f0",
            "zIndex": 1,
            "data": {
              "type": "tm.Actor",
              "name": "User",
              "description": "",
              "outOfScope": false,
              "reasonOutOfScope": "",
              "hasOpenThreats": false,
              "providesAuthentication": false,
              "threats": []
            }
          },
          {
            "position": {
              "x": 307,
              "y": 40
            },
            "size": {
              "width": 112.5,
              "height": 60
            },
            "attrs": {
              "text": {
                "text": "Admin"
              },
              "body": {
                "stroke": "#333333",
                "strokeWidth": 1.5,
                "strokeDasharray": null
              }
            },
            "visible": true,
            "shape": "actor",
            "ports": {
              "groups": {
                "top": {
                  "position": "top",
                  "attrs": {
                    "circle": {
                      "r": 4,
                      "magnet": true,
                      "stroke": "#5F95FF",
                      "strokeWidth": 1,
                      "fill": "#fff",
                      "style": {
                        "visibility": "hidden"
                      }
                    }
                  }
                },
                "right": {
                  "position": "right",
                  "attrs": {
                    "circle": {
                      "r": 4,
                      "magnet": true,
                      "stroke": "#5F95FF",
                      "strokeWidth": 1,
                      "fill": "#fff",
                      "style": {
                        "visibility": "hidden"
                      }
                    }
                  }
                },
                "bottom": {
                  "position": "bottom",
                  "attrs": {
                    "circle": {
                      "r": 4,
                      "magnet": true,
                      "stroke": "#5F95FF",
                      "strokeWidth": 1,
                      "fill": "#fff",
                      "style": {
                        "visibility": "hidden"
                      }
                    }
                  }
                },
                "left": {
                  "position": "left",
                  "attrs": {
                    "circle": {
                      "r": 4,
                      "magnet": true,
                      "stroke": "#5F95FF",
                      "strokeWidth": 1,
                      "fill": "#fff",
                      "style": {
                        "visibility": "hidden"
                      }
                    }
                  }
                }
              },
              "items": [
                {
                  "group": "top",
                  "id": "153955eb-57cb-4855-8cd1-f81644e71db9"
                },
                {
                  "group": "right",
                  "id": "a05692a4-6712-4d97-9964-84bad8ed7c31"
                },
                {
                  "group": "bottom",
                  "id": "0db3e927-0339-4b5e-a037-55e00d40eda3"
                },
                {
                  "group": "left",
                  "id": "27d78f95-7623-4018-ad09-dd3669f7077b"
                }
              ]
            },
            "id": "2840cd55-89a2-4d78-9809-73f244b64a51",
            "zIndex": 2,
            "data": {
              "type": "tm.Actor",
              "name": "Admin",
              "description": "",
              "outOfScope": false,
              "reasonOutOfScope": "",
              "hasOpenThreats": false,
              "providesAuthentication": false,
              "threats": []
            }
          },
          {
            "position": {
              "x": 540,
              "y": 40
            },
            "size": {
              "width": 112.5,
              "height": 60
            },
            "attrs": {
              "text": {
                "text": "Attacker"
              },
              "body": {
                "stroke": "#333333",
                "strokeWidth": 1.5,
                "strokeDasharray": null
              }
            },
            "visible": true,
            "shape": "actor",
            "ports": {
              "groups": {
                "top": {
                  "position": "top",
                  "attrs": {
                    "circle": {
                      "r": 4,
                      "magnet": true,
                      "stroke": "#5F95FF",
                      "strokeWidth": 1,
                      "fill": "#fff",
                      "style": {
                        "visibility": "hidden"
                      }
                    }
                  }
                },
                "right": {
                  "position": "right",
                  "attrs": {
                    "circle": {
                      "r": 4,
                      "magnet": true,
                      "stroke": "#5F95FF",
                      "strokeWidth": 1,
                      "fill": "#fff",
                      "style": {
                        "visibility": "hidden"
                      }
                    }
                  }
                },
                "bottom": {
                  "position": "bottom",
                  "attrs": {
                    "circle": {
                      "r": 4,
                      "magnet": true,
                      "stroke": "#5F95FF",
                      "strokeWidth": 1,
                      "fill": "#fff",
                      "style": {
                        "visibility": "hidden"
                      }
                    }
                  }
                },
                "left": {
                  "position": "left",
                  "attrs": {
                    "circle": {
                      "r": 4,
                      "magnet": true,
                      "stroke": "#5F95FF",
                      "strokeWidth": 1,
                      "fill": "#fff",
                      "style": {
                        "visibility": "hidden"
                      }
                    }
                  }
                }
              },
              "items": [
                {
                  "group": "top",
                  "id": "153955eb-57cb-4855-8cd1-f81644e71db9"
                },
                {
                  "group": "right",
                  "id": "a05692a4-6712-4d97-9964-84bad8ed7c31"
                },
                {
                  "group": "bottom",
                  "id": "0db3e927-0339-4b5e-a037-55e00d40eda3"
                },
                {
                  "group": "left",
                  "id": "27d78f95-7623-4018-ad09-dd3669f7077b"
                }
              ]
            },
            "id": "aca6dd65-53ff-4715-af70-52f67d0ed916",
            "zIndex": 3,
            "data": {
              "type": "tm.Actor",
              "name": "Attacker",
              "description": "",
              "outOfScope": false,
              "reasonOutOfScope": "",
              "hasOpenThreats": false,
              "providesAuthentication": false,
              "threats": []
            }
          },
          {
            "position": {
              "x": 765,
              "y": 40
            },
            "size": {
              "width": 112.5,
              "height": 60
            },
            "attrs": {
              "text": {
                "text": "External\nPayment\nGateway"
              },
              "body": {
                "stroke": "#333333",
                "strokeWidth": 1.5,
                "strokeDasharray": null
              }
            },
            "visible": true,
            "shape": "actor",
            "ports": {
              "groups": {
                "top": {
                  "position": "top",
                  "attrs": {
                    "circle": {
                      "r": 4,
                      "magnet": true,
                      "stroke": "#5F95FF",
                      "strokeWidth": 1,
                      "fill": "#fff",
                      "style": {
                        "visibility": "hidden"
                      }
                    }
                  }
                },
                "right": {
                  "position": "right",
                  "attrs": {
                    "circle": {
                      "r": 4,
                      "magnet": true,
                      "stroke": "#5F95FF",
                      "strokeWidth": 1,
                      "fill": "#fff",
                      "style": {
                        "visibility": "hidden"
                      }
                    }
                  }
                },
                "bottom": {
                  "position": "bottom",
                  "attrs": {
                    "circle": {
                      "r": 4,
                      "magnet": true,
                      "stroke": "#5F95FF",
                      "strokeWidth": 1,
                      "fill": "#fff",
                      "style": {
                        "visibility": "hidden"
                      }
                    }
                  }
                },
                "left": {
                  "position": "left",
                  "attrs": {
                    "circle": {
                      "r": 4,
                      "magnet": true,
                      "stroke": "#5F95FF",
                      "strokeWidth": 1,
                      "fill": "#fff",
                      "style": {
                        "visibility": "hidden"
                      }
                    }
                  }
                }
              },
              "items": [
                {
                  "group": "top",
                  "id": "153955eb-57cb-4855-8cd1-f81644e71db9"
                },
                {
                  "group": "right",
                  "id": "a05692a4-6712-4d97-9964-84bad8ed7c31"
                },
                {
                  "group": "bottom",
                  "id": "0db3e927-0339-4b5e-a037-55e00d40eda3"
                },
                {
                  "group": "left",
                  "id": "27d78f95-7623-4018-ad09-dd3669f7077b"
                }
              ]
            },
            "id": "6575990f-1fc8-4f07-b1fb-1c4b2718443d",
            "zIndex": 4,
            "data": {
              "type": "tm.Actor",
              "name": "External\nPayment\nGateway",
              "description": "",
              "outOfScope": false,
              "reasonOutOfScope": "",
              "hasOpenThreats": false,
              "providesAuthentication": false,
              "threats": []
            }
          },
          {
            "position": {
              "x": 101.25,
              "y": 175
            },
            "size": {
              "width": 90,
              "height": 90
            },
            "attrs": {
              "text": {
                "text": "Login\nService"
              },
              "body": {
                "stroke": "#333333",
                "strokeWidth": 1.5,
                "strokeDasharray": null
              }
            },
            "visible": true,
            "shape": "process",
            "ports": {
              "groups": {
                "top": {
                  "position": "top",
                  "attrs": {
                    "circle": {
                      "r": 4,
                      "magnet": true,
                      "stroke": "#5F95FF",
                      "strokeWidth": 1,
                      "fill": "#fff",
                      "style": {
                        "visibility": "hidden"
                      }
                    }
                  }
                },
                "right": {
                  "position": "right",
                  "attrs": {
                    "circle": {
                      "r": 4,
                      "magnet": true,
                      "stroke": "#5F95FF",
                      "strokeWidth": 1,
                      "fill": "#fff",
                      "style": {
                        "visibility": "hidden"
                      }
                    }
                  }
                },
                "bottom": {
                  "position": "bottom",
                  "attrs": {
                    "circle": {
                      "r": 4,
                      "magnet": true,
                      "stroke": "#5F95FF",
                      "strokeWidth": 1,
                      "fill": "#fff",
                      "style": {
                        "visibility": "hidden"
                      }
                    }
                  }
                },
                "left": {
                  "position": "left",
                  "attrs": {
                    "circle": {
                      "r": 4,
                      "magnet": true,
                      "stroke": "#5F95FF",
                      "strokeWidth": 1,
                      "fill": "#fff",
                      "style": {
                        "visibility": "hidden"
                      }
                    }
                  }
                }
              },
              "items": [
                {
                  "group": "top",
                  "id": "e73acfab-b19f-45fa-ab42-48b9a7c041f7"
                },
                {
                  "group": "right",
                  "id": "65171a17-8102-4a67-a475-31ff04533d51"
                },
                {
                  "group": "bottom",
                  "id": "4ba16168-3c48-4a92-bc95-c18c3d8e95f0"
                },
                {
                  "group": "left",
                  "id": "f63289e5-6e50-4f12-aec4-92786ac5d928"
                }
              ]
            },
            "id": "4010bc21-f6fa-482b-b87d-6d777f7fc134",
            "zIndex": 5,
            "data": {
              "type": "tm.Process",
              "name": "Login\nService",
              "description": "",
              "outOfScope": false,
              "reasonOutOfScope": "",
              "hasOpenThreats": false,
              "handlesCardPayment": false,
              "handlesGoodsOrServices": false,
              "isWebApplication": false,
              "privilegeLevel": "",
              "threats": []
            }
          },
          {
            "position": {
              "x": 318.25,
              "y": 175
            },
            "size": {
              "width": 90,
              "height": 90
            },
            "attrs": {
              "text": {
                "text": "Admin\nInterface"
              },
              "body": {
                "stroke": "#333333",
                "strokeWidth": 1.5,
                "strokeDasharray": null
              }
            },
            "visible": true,
            "shape": "process",
            "ports": {
              "groups": {
                "top": {
                  "position": "top",
                  "attrs": {
                    "circle": {
                      "r": 4,
                      "magnet": true,
                      "stroke": "#5F95FF",
                      "strokeWidth": 1,
                      "fill": "#fff",
                      "style": {
                        "visibility": "hidden"
                      }
                    }
                  }
                },
                "right": {
                  "position": "right",
                  "attrs": {
                    "circle": {
                      "r": 4,
                      "magnet": true,
                      "stroke": "#5F95FF",
                      "strokeWidth": 1,
                      "fill": "#fff",
                      "style": {
                        "visibility": "hidden"
                      }
                    }
                  }
                },
                "bottom": {
                  "position": "bottom",
                  "attrs": {
                    "circle": {
                      "r": 4,
                      "magnet": true,
                      "stroke": "#5F95FF",
                      "strokeWidth": 1,
                      "fill": "#fff",
                      "style": {
                        "visibility": "hidden"
                      }
                    }
                  }
                },
                "left": {
                  "position": "left",
                  "attrs": {
                    "circle": {
                      "r": 4,
                      "magnet": true,
                      "stroke": "#5F95FF",
                      "strokeWidth": 1,
                      "fill": "#fff",
                      "style": {
                        "visibility": "hidden"
                      }
                    }
                  }
                }
              },
              "items": [
                {
                  "group": "top",
                  "id": "e73acfab-b19f-45fa-ab42-48b9a7c041f7"
                },
                {
                  "group": "right",
                  "id": "65171a17-8102-4a67-a475-31ff04533d51"
                },
                {
                  "group": "bottom",
                  "id": "4ba16168-3c48-4a92-bc95-c18c3d8e95f0"
                },
                {
                  "group": "left",
                  "id": "f63289e5-6e50-4f12-aec4-92786ac5d928"
                }
              ]
            },
            "id": "869aa9e5-7452-47cf-a27d-bd856d3a80aa",
            "zIndex": 6,
            "data": {
              "type": "tm.Process",
              "name": "Admin\nInterface",
              "description": "",
              "outOfScope": false,
              "reasonOutOfScope": "",
              "hasOpenThreats": false,
              "handlesCardPayment": false,
              "handlesGoodsOrServices": false,
              "isWebApplication": false,
              "privilegeLevel": "",
              "threats": []
            }
          },
          {
            "position": {
              "x": 541.25,
              "y": 185
            },
            "size": {
              "width": 110,
              "height": 90
            },
            "attrs": {
              "text": {
                "text": "Session\nManagement\nService"
              },
              "body": {
                "stroke": "#333333",
                "strokeWidth": 1.5,
                "strokeDasharray": null
              }
            },
            "visible": true,
            "shape": "process",
            "ports": {
              "groups": {
                "top": {
                  "position": "top",
                  "attrs": {
                    "circle": {
                      "r": 4,
                      "magnet": true,
                      "stroke": "#5F95FF",
                      "strokeWidth": 1,
                      "fill": "#fff",
                      "style": {
                        "visibility": "hidden"
                      }
                    }
                  }
                },
                "right": {
                  "position": "right",
                  "attrs": {
                    "circle": {
                      "r": 4,
                      "magnet": true,
                      "stroke": "#5F95FF",
                      "strokeWidth": 1,
                      "fill": "#fff",
                      "style": {
                        "visibility": "hidden"
                      }
                    }
                  }
                },
                "bottom": {
                  "position": "bottom",
                  "attrs": {
                    "circle": {
                      "r": 4,
                      "magnet": true,
                      "stroke": "#5F95FF",
                      "strokeWidth": 1,
                      "fill": "#fff",
                      "style": {
                        "visibility": "hidden"
                      }
                    }
                  }
                },
                "left": {
                  "position": "left",
                  "attrs": {
                    "circle": {
                      "r": 4,
                      "magnet": true,
                      "stroke": "#5F95FF",
                      "strokeWidth": 1,
                      "fill": "#fff",
                      "style": {
                        "visibility": "hidden"
                      }
                    }
                  }
                }
              },
              "items": [
                {
                  "group": "top",
                  "id": "e73acfab-b19f-45fa-ab42-48b9a7c041f7"
                },
                {
                  "group": "right",
                  "id": "65171a17-8102-4a67-a475-31ff04533d51"
                },
                {
                  "group": "bottom",
                  "id": "4ba16168-3c48-4a92-bc95-c18c3d8e95f0"
                },
                {
                  "group": "left",
                  "id": "f63289e5-6e50-4f12-aec4-92786ac5d928"
                }
              ]
            },
            "id": "f63f85b7-42bb-451c-ba8d-349722516c25",
            "zIndex": 7,
            "data": {
              "type": "tm.Process",
              "name": "Session\nManagement\nService",
              "description": "",
              "outOfScope": false,
              "reasonOutOfScope": "",
              "hasOpenThreats": false,
              "handlesCardPayment": false,
              "handlesGoodsOrServices": false,
              "isWebApplication": false,
              "privilegeLevel": "",
              "threats": []
            }
          },
          {
            "position": {
              "x": 777.5,
              "y": 175
            },
            "size": {
              "width": 100,
              "height": 90
            },
            "attrs": {
              "text": {
                "text": "Notification\nService"
              },
              "body": {
                "stroke": "#333333",
                "strokeWidth": 1.5,
                "strokeDasharray": null
              }
            },
            "visible": true,
            "shape": "process",
            "ports": {
              "groups": {
                "top": {
                  "position": "top",
                  "attrs": {
                    "circle": {
                      "r": 4,
                      "magnet": true,
                      "stroke": "#5F95FF",
                      "strokeWidth": 1,
                      "fill": "#fff",
                      "style": {
                        "visibility": "hidden"
                      }
                    }
                  }
                },
                "right": {
                  "position": "right",
                  "attrs": {
                    "circle": {
                      "r": 4,
                      "magnet": true,
                      "stroke": "#5F95FF",
                      "strokeWidth": 1,
                      "fill": "#fff",
                      "style": {
                        "visibility": "hidden"
                      }
                    }
                  }
                },
                "bottom": {
                  "position": "bottom",
                  "attrs": {
                    "circle": {
                      "r": 4,
                      "magnet": true,
                      "stroke": "#5F95FF",
                      "strokeWidth": 1,
                      "fill": "#fff",
                      "style": {
                        "visibility": "hidden"
                      }
                    }
                  }
                },
                "left": {
                  "position": "left",
                  "attrs": {
                    "circle": {
                      "r": 4,
                      "magnet": true,
                      "stroke": "#5F95FF",
                      "strokeWidth": 1,
                      "fill": "#fff",
                      "style": {
                        "visibility": "hidden"
                      }
                    }
                  }
                }
              },
              "items": [
                {
                  "group": "top",
                  "id": "e73acfab-b19f-45fa-ab42-48b9a7c041f7"
                },
                {
                  "group": "right",
                  "id": "65171a17-8102-4a67-a475-31ff04533d51"
                },
                {
                  "group": "bottom",
                  "id": "4ba16168-3c48-4a92-bc95-c18c3d8e95f0"
                },
                {
                  "group": "left",
                  "id": "f63289e5-6e50-4f12-aec4-92786ac5d928"
                }
              ]
            },
            "id": "b6e73a42-b110-4bff-96d0-26d3c2546083",
            "zIndex": 8,
            "data": {
              "type": "tm.Process",
              "name": "Notification\nService",
              "description": "",
              "outOfScope": false,
              "reasonOutOfScope": "",
              "hasOpenThreats": false,
              "handlesCardPayment": false,
              "handlesGoodsOrServices": false,
              "isWebApplication": false,
              "privilegeLevel": "",
              "threats": []
            }
          },
          {
            "position": {
              "x": 820,
              "y": 400
            },
            "size": {
              "width": 120,
              "height": 60
            },
            "attrs": {
              "text": {
                "text": "Transaction Logs"
              },
              "topLine": {
                "strokeWidth": 1.5,
                "strokeDasharray": null
              },
              "bottomLine": {
                "strokeWidth": 1.5,
                "strokeDasharray": null
              }
            },
            "visible": true,
            "shape": "store",
            "ports": {
              "groups": {
                "top": {
                  "position": "top",
                  "attrs": {
                    "circle": {
                      "r": 4,
                      "magnet": true,
                      "stroke": "#5F95FF",
                      "strokeWidth": 1,
                      "fill": "#fff",
                      "style": {
                        "visibility": "hidden"
                      }
                    }
                  }
                },
                "right": {
                  "position": "right",
                  "attrs": {
                    "circle": {
                      "r": 4,
                      "magnet": true,
                      "stroke": "#5F95FF",
                      "strokeWidth": 1,
                      "fill": "#fff",
                      "style": {
                        "visibility": "hidden"
                      }
                    }
                  }
                },
                "bottom": {
                  "position": "bottom",
                  "attrs": {
                    "circle": {
                      "r": 4,
                      "magnet": true,
                      "stroke": "#5F95FF",
                      "strokeWidth": 1,
                      "fill": "#fff",
                      "style": {
                        "visibility": "hidden"
                      }
                    }
                  }
                },
                "left": {
                  "position": "left",
                  "attrs": {
                    "circle": {
                      "r": 4,
                      "magnet": true,
                      "stroke": "#5F95FF",
                      "strokeWidth": 1,
                      "fill": "#fff",
                      "style": {
                        "visibility": "hidden"
                      }
                    }
                  }
                }
              },
              "items": [
                {
                  "group": "top",
                  "id": "837a0656-dd4c-4d4a-841b-160e371b05fb"
                },
                {
                  "group": "right",
                  "id": "24567379-2a52-4b55-b025-2ea4afe2af5b"
                },
                {
                  "group": "bottom",
                  "id": "48e49c69-c69a-4a00-ac37-b182949fb10f"
                },
                {
                  "group": "left",
                  "id": "79b89502-7164-4cb6-ac65-d4f3b4298d1b"
                }
              ]
            },
            "id": "86349400-e50e-467b-ad90-27093fe274d0",
            "zIndex": 9,
            "data": {
              "type": "tm.Store",
              "name": "Transaction Logs",
              "description": "",
              "outOfScope": false,
              "reasonOutOfScope": "",
              "hasOpenThreats": false,
              "isALog": false,
              "isEncrypted": false,
              "isSigned": false,
              "storesCredentials": false,
              "storesInventory": false,
              "threats": []
            }
          },
          {
            "position": {
              "x": 81.25,
              "y": 405
            },
            "size": {
              "width": 130,
              "height": 50
            },
            "attrs": {
              "text": {
                "text": "Users Database"
              },
              "topLine": {
                "strokeWidth": 1.5,
                "strokeDasharray": null
              },
              "bottomLine": {
                "strokeWidth": 1.5,
                "strokeDasharray": null
              }
            },
            "visible": true,
            "shape": "store",
            "ports": {
              "groups": {
                "top": {
                  "position": "top",
                  "attrs": {
                    "circle": {
                      "r": 4,
                      "magnet": true,
                      "stroke": "#5F95FF",
                      "strokeWidth": 1,
                      "fill": "#fff",
                      "style": {
                        "visibility": "hidden"
                      }
                    }
                  }
                },
                "right": {
                  "position": "right",
                  "attrs": {
                    "circle": {
                      "r": 4,
                      "magnet": true,
                      "stroke": "#5F95FF",
                      "strokeWidth": 1,
                      "fill": "#fff",
                      "style": {
                        "visibility": "hidden"
                      }
                    }
                  }
                },
                "bottom": {
                  "position": "bottom",
                  "attrs": {
                    "circle": {
                      "r": 4,
                      "magnet": true,
                      "stroke": "#5F95FF",
                      "strokeWidth": 1,
                      "fill": "#fff",
                      "style": {
                        "visibility": "hidden"
                      }
                    }
                  }
                },
                "left": {
                  "position": "left",
                  "attrs": {
                    "circle": {
                      "r": 4,
                      "magnet": true,
                      "stroke": "#5F95FF",
                      "strokeWidth": 1,
                      "fill": "#fff",
                      "style": {
                        "visibility": "hidden"
                      }
                    }
                  }
                }
              },
              "items": [
                {
                  "group": "top",
                  "id": "837a0656-dd4c-4d4a-841b-160e371b05fb"
                },
                {
                  "group": "right",
                  "id": "24567379-2a52-4b55-b025-2ea4afe2af5b"
                },
                {
                  "group": "bottom",
                  "id": "48e49c69-c69a-4a00-ac37-b182949fb10f"
                },
                {
                  "group": "left",
                  "id": "79b89502-7164-4cb6-ac65-d4f3b4298d1b"
                }
              ]
            },
            "id": "4e8352dd-bd4f-4569-ba4d-ca7608c36db3",
            "zIndex": 10,
            "data": {
              "type": "tm.Store",
              "name": "Users Database",
              "description": "",
              "outOfScope": false,
              "reasonOutOfScope": "",
              "hasOpenThreats": false,
              "isALog": false,
              "isEncrypted": false,
              "isSigned": false,
              "storesCredentials": false,
              "storesInventory": false,
              "threats": []
            }
          },
          {
            "shape": "flow",
            "attrs": {
              "line": {
                "stroke": "#333333",
                "targetMarker": {
                  "name": "block"
                },
                "sourceMarker": {
                  "name": ""
                },
                "strokeDasharray": null
              }
            },
            "width": 200,
            "height": 100,
            "zIndex": 10,
            "connector": "smooth",
            "data": {
              "type": "tm.Flow",
              "name": "User \nLogin\nRequest",
              "description": "Sends username and password to log in",
              "outOfScope": false,
              "reasonOutOfScope": "",
              "hasOpenThreats": false,
              "isBidirectional": false,
              "isEncrypted": false,
              "isPublicNetwork": false,
              "protocol": "",
              "threats": []
            },
            "labels": [
              "User \nLogin\nRequest"
            ],
            "id": "b2cf6fab-ba27-4c9b-887e-4ebc6979e32a",
            "source": {
              "x": 119,
              "y": 100
            },
            "target": {
              "cell": "4010bc21-f6fa-482b-b87d-6d777f7fc134",
              "port": "e73acfab-b19f-45fa-ab42-48b9a7c041f7"
            }
          },
          {
            "shape": "flow",
            "attrs": {
              "line": {
                "stroke": "#333333",
                "targetMarker": {
                  "name": "block"
                },
                "sourceMarker": {
                  "name": ""
                },
                "strokeDasharray": null
              }
            },
            "width": 200,
            "height": 100,
            "zIndex": 10,
            "connector": "smooth",
            "data": {
              "type": "tm.Flow",
              "name": "Generate\nSession\nToken",
              "description": "Creates a session token after successful login",
              "outOfScope": false,
              "reasonOutOfScope": "",
              "hasOpenThreats": false,
              "isBidirectional": false,
              "isEncrypted": false,
              "isPublicNetwork": false,
              "protocol": "",
              "threats": []
            },
            "labels": [
              "Generate\nSession\nToken"
            ],
            "id": "c90c21f0-3309-43e0-ae1a-1285e46660d5",
            "source": {
              "x": 142,
              "y": 265
            },
            "target": {
              "cell": "f63f85b7-42bb-451c-ba8d-349722516c25",
              "port": "4ba16168-3c48-4a92-bc95-c18c3d8e95f0"
            },
            "vertices": [
              {
                "x": 350,
                "y": 300
              }
            ]
          },
          {
            "shape": "flow",
            "attrs": {
              "line": {
                "stroke": "#333333",
                "targetMarker": {
                  "name": "block"
                },
                "sourceMarker": {
                  "name": ""
                },
                "strokeDasharray": null
              }
            },
            "width": 200,
            "height": 100,
            "zIndex": 10,
            "connector": "smooth",
            "data": {
              "type": "tm.Flow",
              "name": "Session\nToken\nValidation",
              "description": "",
              "outOfScope": false,
              "reasonOutOfScope": "",
              "hasOpenThreats": false,
              "isBidirectional": false,
              "isEncrypted": false,
              "isPublicNetwork": false,
              "protocol": "",
              "threats": []
            },
            "labels": [
              "Session\nToken\nValidation"
            ],
            "id": "60254ef7-df78-4139-90c4-b6238cd0e5ec",
            "source": {
              "x": 641,
              "y": 233
            },
            "target": {
              "cell": "9d2a0241-a883-4dab-94d9-eb71e01b9c67",
              "port": "65171a17-8102-4a67-a475-31ff04533d51"
            },
            "vertices": [
              {
                "x": 590,
                "y": 320
              }
            ]
          },
          {
            "shape": "flow",
            "attrs": {
              "line": {
                "stroke": "#333333",
                "targetMarker": {
                  "name": "block"
                },
                "sourceMarker": {
                  "name": ""
                },
                "strokeDasharray": null
              }
            },
            "width": 200,
            "height": 100,
            "zIndex": 10,
            "connector": "smooth",
            "data": {
              "type": "tm.Flow",
              "name": "Validate\nAdmin\nSession",
              "description": "Validates session for privileged access",
              "outOfScope": false,
              "reasonOutOfScope": "",
              "hasOpenThreats": false,
              "isBidirectional": false,
              "isEncrypted": false,
              "isPublicNetwork": false,
              "protocol": "",
              "threats": []
            },
            "labels": [
              "Validate\nAdmin\nSession"
            ],
            "id": "8b200ede-0a43-4bf8-8eb2-ce088fdf8564",
            "source": {
              "x": 408,
              "y": 215
            },
            "target": {
              "cell": "f63f85b7-42bb-451c-ba8d-349722516c25",
              "port": "f63289e5-6e50-4f12-aec4-92786ac5d928"
            }
          },
          {
            "shape": "flow",
            "attrs": {
              "line": {
                "stroke": "#333333",
                "targetMarker": {
                  "name": "block"
                },
                "sourceMarker": {
                  "name": ""
                },
                "strokeDasharray": null
              }
            },
            "width": 200,
            "height": 100,
            "zIndex": 10,
            "connector": "smooth",
            "data": {
              "type": "tm.Flow",
              "name": "Trigger\nUser\nNotification",
              "description": "Sends request to notify the user",
              "outOfScope": false,
              "reasonOutOfScope": "",
              "hasOpenThreats": false,
              "isBidirectional": false,
              "isEncrypted": false,
              "isPublicNetwork": false,
              "protocol": "",
              "threats": []
            },
            "labels": [
              "Trigger\nUser\nNotification"
            ],
            "id": "9c62a4a4-5250-44dd-ba24-e5fabfed0d25",
            "source": {
              "x": 470,
              "y": 433
            },
            "target": {
              "cell": "b6e73a42-b110-4bff-96d0-26d3c2546083",
              "port": "4ba16168-3c48-4a92-bc95-c18c3d8e95f0"
            },
            "vertices": [
              {
                "x": 680,
                "y": 350
              }
            ]
          },
          {
            "shape": "flow",
            "attrs": {
              "line": {
                "stroke": "#333333",
                "targetMarker": {
                  "name": "block"
                },
                "sourceMarker": {
                  "name": ""
                },
                "strokeDasharray": null
              }
            },
            "width": 200,
            "height": 100,
            "zIndex": 10,
            "connector": "smooth",
            "data": {
              "type": "tm.Flow",
              "name": "Deliver Notification",
              "description": "",
              "outOfScope": false,
              "reasonOutOfScope": "",
              "hasOpenThreats": false,
              "isBidirectional": false,
              "isEncrypted": false,
              "isPublicNetwork": false,
              "protocol": "",
              "threats": []
            },
            "labels": [
              "Deliver Notification"
            ],
            "id": "31f6d3a3-1320-436a-b6d8-eb7b53396ea6",
            "source": {
              "cell": "b6e73a42-b110-4bff-96d0-26d3c2546083",
              "port": "65171a17-8102-4a67-a475-31ff04533d51"
            },
            "target": {
              "cell": "8ddb3e65-40db-43a5-ae79-f6d4bd2789f0",
              "port": "153955eb-57cb-4855-8cd1-f81644e71db9"
            },
            "vertices": [
              {
                "x": 860,
                "y": 20
              }
            ]
          },
          {
            "shape": "flow",
            "attrs": {
              "line": {
                "stroke": "#333333",
                "targetMarker": {
                  "name": "block"
                },
                "sourceMarker": {
                  "name": ""
                },
                "strokeDasharray": null
              }
            },
            "width": 200,
            "height": 100,
            "zIndex": 10,
            "connector": "smooth",
            "data": {
              "type": "tm.Flow",
              "name": "Log \nTransaction \nDetails",
              "description": "",
              "outOfScope": false,
              "reasonOutOfScope": "",
              "hasOpenThreats": false,
              "isBidirectional": false,
              "isEncrypted": false,
              "isPublicNetwork": false,
              "protocol": "",
              "threats": []
            },
            "labels": [
              "Log \nTransaction \nDetails"
            ],
            "id": "24a365e4-a920-4ae4-9528-ee7f5fd9b37b",
            "source": {
              "x": 501,
              "y": 423
            },
            "target": {
              "cell": "86349400-e50e-467b-ad90-27093fe274d0",
              "port": "48e49c69-c69a-4a00-ac37-b182949fb10f"
            }
          },
          {
            "shape": "flow",
            "attrs": {
              "line": {
                "stroke": "#333333",
                "targetMarker": {
                  "name": "block"
                },
                "sourceMarker": {
                  "name": ""
                },
                "strokeDasharray": null
              }
            },
            "width": 200,
            "height": 100,
            "zIndex": 10,
            "connector": "smooth",
            "data": {
              "type": "tm.Flow",
              "name": "Send\nPayment for\nprocessing",
              "description": "",
              "outOfScope": false,
              "reasonOutOfScope": "",
              "hasOpenThreats": false,
              "isBidirectional": false,
              "isEncrypted": false,
              "isPublicNetwork": false,
              "protocol": "",
              "threats": []
            },
            "labels": [
              "Send\nPayment for\nprocessing"
            ],
            "id": "85165157-bd47-42ef-86d3-2bc577508509",
            "source": {
              "x": 531,
              "y": 390
            },
            "target": {
              "cell": "6575990f-1fc8-4f07-b1fb-1c4b2718443d",
              "port": "0db3e927-0339-4b5e-a037-55e00d40eda3"
            },
            "vertices": [
              {
                "x": 960,
                "y": 340
              }
            ]
          },
          {
            "shape": "flow",
            "attrs": {
              "line": {
                "stroke": "#333333",
                "targetMarker": {
                  "name": "block"
                },
                "sourceMarker": {
                  "name": ""
                },
                "strokeDasharray": null
              }
            },
            "width": 200,
            "height": 100,
            "zIndex": 10,
            "connector": "smooth",
            "data": {
              "type": "tm.Flow",
              "name": "Receive\nPayment\nResponse",
              "description": "",
              "outOfScope": false,
              "reasonOutOfScope": "",
              "hasOpenThreats": false,
              "isBidirectional": false,
              "isEncrypted": false,
              "isPublicNetwork": false,
              "protocol": "",
              "threats": []
            },
            "labels": [
              "Receive\nPayment\nResponse"
            ],
            "id": "81adddcb-6ae0-48c9-954e-8b724bd29ff4",
            "source": {
              "x": 878,
              "y": 65
            },
            "target": {
              "cell": "9d2a0241-a883-4dab-94d9-eb71e01b9c67",
              "port": "4ba16168-3c48-4a92-bc95-c18c3d8e95f0"
            },
            "vertices": [
              {
                "x": 878,
                "y": 280
              },
              {
                "x": 830,
                "y": 320
              },
              {
                "x": 780,
                "y": 360
              }
            ]
          },
          {
            "shape": "flow",
            "attrs": {
              "line": {
                "stroke": "#333333",
                "targetMarker": {
                  "name": "block"
                },
                "sourceMarker": {
                  "name": ""
                },
                "strokeDasharray": null
              }
            },
            "width": 200,
            "height": 100,
            "zIndex": 10,
            "connector": "smooth",
            "data": {
              "type": "tm.Flow",
              "name": "Brute\nForce\nLogin\nAttempt",
              "description": "",
              "outOfScope": false,
              "reasonOutOfScope": "",
              "hasOpenThreats": false,
              "isBidirectional": false,
              "isEncrypted": false,
              "isPublicNetwork": false,
              "protocol": "",
              "threats": []
            },
            "labels": [
              "Brute\nForce\nLogin\nAttempt"
            ],
            "id": "c0bdd745-e571-4fdf-ba3c-62ff587744d0",
            "source": {
              "x": 541,
              "y": 70
            },
            "target": {
              "cell": "4010bc21-f6fa-482b-b87d-6d777f7fc134",
              "port": "65171a17-8102-4a67-a475-31ff04533d51"
            },
            "vertices": [
              {
                "x": 430,
                "y": 130
              },
              {
                "x": 390,
                "y": 130
              }
            ]
          },
          {
            "shape": "flow",
            "attrs": {
              "line": {
                "stroke": "#333333",
                "targetMarker": {
                  "name": "block"
                },
                "sourceMarker": {
                  "name": ""
                },
                "strokeDasharray": null
              }
            },
            "width": 200,
            "height": 100,
            "zIndex": 10,
            "connector": "smooth",
            "data": {
              "type": "tm.Flow",
              "name": "Admin\nLogin\nRequest",
              "description": "",
              "outOfScope": false,
              "reasonOutOfScope": "",
              "hasOpenThreats": false,
              "isBidirectional": false,
              "isEncrypted": false,
              "isPublicNetwork": false,
              "protocol": "",
              "threats": []
            },
            "labels": [
              "Admin\nLogin\nRequest"
            ],
            "id": "b771b8f0-2555-4940-91a3-1aece8228b40",
            "source": {
              "x": 354,
              "y": 100
            },
            "target": {
              "cell": "869aa9e5-7452-47cf-a27d-bd856d3a80aa",
              "port": "f63289e5-6e50-4f12-aec4-92786ac5d928"
            },
            "vertices": [
              {
                "x": 280,
                "y": 160
              }
            ]
          },
          {
            "shape": "flow",
            "attrs": {
              "line": {
                "stroke": "#333333",
                "targetMarker": {
                  "name": "block"
                },
                "sourceMarker": {
                  "name": ""
                },
                "strokeDasharray": null
              }
            },
            "width": 200,
            "height": 100,
            "zIndex": 10,
            "connector": "smooth",
            "data": {
              "type": "tm.Flow",
              "name": "Admin\nPrivilege\nExploit\nAttempt",
              "description": "",
              "outOfScope": false,
              "reasonOutOfScope": "",
              "hasOpenThreats": false,
              "isBidirectional": false,
              "isEncrypted": false,
              "isPublicNetwork": false,
              "protocol": "",
              "threats": []
            },
            "labels": [
              "Admin\nPrivilege\nExploit\nAttempt"
            ],
            "id": "fd6e0e1b-5cc9-4de3-b86f-0984c107c285",
            "source": {
              "x": 653,
              "y": 69
            },
            "target": {
              "cell": "869aa9e5-7452-47cf-a27d-bd856d3a80aa",
              "port": "65171a17-8102-4a67-a475-31ff04533d51"
            },
            "vertices": [
              {
                "x": 653,
                "y": 120
              },
              {
                "x": 520,
                "y": 140
              },
              {
                "x": 470,
                "y": 180
              }
            ]
          },
          {
            "shape": "flow",
            "attrs": {
              "line": {
                "stroke": "#333333",
                "targetMarker": {
                  "name": "block"
                },
                "sourceMarker": {
                  "name": ""
                },
                "strokeDasharray": null
              }
            },
            "width": 200,
            "height": 100,
            "zIndex": 10,
            "connector": "smooth",
            "data": {
              "type": "tm.Flow",
              "name": "Malicious\nAPI\nAttack",
              "description": "",
              "outOfScope": false,
              "reasonOutOfScope": "",
              "hasOpenThreats": false,
              "isBidirectional": false,
              "isEncrypted": false,
              "isPublicNetwork": false,
              "protocol": "",
              "threats": []
            },
            "labels": [
              "Malicious\nAPI\nAttack"
            ],
            "id": "6462115b-10d3-4002-bfc3-6973be66442d",
            "source": {
              "x": 586,
              "y": 100
            },
            "target": {
              "cell": "9d2a0241-a883-4dab-94d9-eb71e01b9c67",
              "port": "e73acfab-b19f-45fa-ab42-48b9a7c041f7"
            },
            "vertices": [
              {
                "x": 730,
                "y": 230
              },
              {
                "x": 650,
                "y": 333
              }
            ]
          },
          {
            "shape": "flow",
            "attrs": {
              "line": {
                "stroke": "#333333",
                "targetMarker": {
                  "name": "block"
                },
                "sourceMarker": {
                  "name": ""
                },
                "strokeDasharray": null
              }
            },
            "width": 200,
            "height": 100,
            "zIndex": 10,
            "connector": "smooth",
            "data": {
              "type": "tm.Flow",
              "name": "Retrieve\nUser\nProfile",
              "description": "",
              "outOfScope": false,
              "reasonOutOfScope": "",
              "hasOpenThreats": false,
              "isBidirectional": false,
              "isEncrypted": false,
              "isPublicNetwork": false,
              "protocol": "",
              "threats": []
            },
            "labels": [
              "Retrieve\nUser\nProfile"
            ],
            "id": "d11ba055-10a6-42f4-a3e4-c886a33f7293",
            "source": {
              "cell": "9d2a0241-a883-4dab-94d9-eb71e01b9c67",
              "port": "f63289e5-6e50-4f12-aec4-92786ac5d928"
            },
            "target": {
              "cell": "4e8352dd-bd4f-4569-ba4d-ca7608c36db3",
              "port": "24567379-2a52-4b55-b025-2ea4afe2af5b"
            },
            "vertices": [
              {
                "x": 310,
                "y": 480
              },
              {
                "x": 260,
                "y": 453
              }
            ]
          },
          {
            "position": {
              "x": 364.5,
              "y": 475
            },
            "size": {
              "width": 90,
              "height": 100
            },
            "attrs": {
              "text": {
                "text": "API Gateway"
              },
              "body": {
                "stroke": "#333333",
                "strokeWidth": 1.5,
                "strokeDasharray": null
              }
            },
            "visible": true,
            "shape": "process",
            "ports": {
              "groups": {
                "top": {
                  "position": "top",
                  "attrs": {
                    "circle": {
                      "r": 4,
                      "magnet": true,
                      "stroke": "#5F95FF",
                      "strokeWidth": 1,
                      "fill": "#fff",
                      "style": {
                        "visibility": "hidden"
                      }
                    }
                  }
                },
                "right": {
                  "position": "right",
                  "attrs": {
                    "circle": {
                      "r": 4,
                      "magnet": true,
                      "stroke": "#5F95FF",
                      "strokeWidth": 1,
                      "fill": "#fff",
                      "style": {
                        "visibility": "hidden"
                      }
                    }
                  }
                },
                "bottom": {
                  "position": "bottom",
                  "attrs": {
                    "circle": {
                      "r": 4,
                      "magnet": true,
                      "stroke": "#5F95FF",
                      "strokeWidth": 1,
                      "fill": "#fff",
                      "style": {
                        "visibility": "hidden"
                      }
                    }
                  }
                },
                "left": {
                  "position": "left",
                  "attrs": {
                    "circle": {
                      "r": 4,
                      "magnet": true,
                      "stroke": "#5F95FF",
                      "strokeWidth": 1,
                      "fill": "#fff",
                      "style": {
                        "visibility": "hidden"
                      }
                    }
                  }
                }
              },
              "items": [
                {
                  "group": "top",
                  "id": "e73acfab-b19f-45fa-ab42-48b9a7c041f7"
                },
                {
                  "group": "right",
                  "id": "65171a17-8102-4a67-a475-31ff04533d51"
                },
                {
                  "group": "bottom",
                  "id": "4ba16168-3c48-4a92-bc95-c18c3d8e95f0"
                },
                {
                  "group": "left",
                  "id": "f63289e5-6e50-4f12-aec4-92786ac5d928"
                }
              ]
            },
            "id": "9d2a0241-a883-4dab-94d9-eb71e01b9c67",
            "zIndex": 11,
            "data": {
              "type": "tm.Process",
              "name": "API Gateway",
              "description": "",
              "outOfScope": false,
              "reasonOutOfScope": "",
              "hasOpenThreats": false,
              "handlesCardPayment": false,
              "handlesGoodsOrServices": false,
              "isWebApplication": false,
              "privilegeLevel": "",
              "threats": []
            }
          }
        ],
        "description": "Threat model diagram for Stellar Pay's web app components"
      }
    ],
    "diagramTop": 3,
    "reviewer": "",
    "threatTop": 0
  }
}